LICENSE
README.md
setup.py
challonge/__init__.py
challonge/api.py
challonge/attachments.py
challonge/matches.py
challonge/participants.py
challonge/tournaments.py
pychallonge.egg-info/PKG-INFO
pychallonge.egg-info/SOURCES.txt
pychallonge.egg-info/dependency_links.txt
pychallonge.egg-info/requires.txt
pychallonge.egg-info/top_level.txt