Metadata-Version: 2.1
Name: pychallonge
Version: 1.11.5
Summary: Α python module to use the Challonge API
Home-page: https://github.com/ZEDGR/pychallonge
Author: ZEDGR
Author-email: georlema@gmail.com
License: Public Domain
Keywords: tournaments,challonge
Platform: any
Classifier: Development Status :: 5 - Production/Stable
Classifier: Intended Audience :: Developers
Classifier: License :: Public Domain
Classifier: Operating System :: OS Independent
Classifier: Programming Language :: Python :: 2
Classifier: Programming Language :: Python :: 2.7
Classifier: Programming Language :: Python :: 3
Classifier: Programming Language :: Python :: 3.4
Classifier: Programming Language :: Python :: 3.5
Classifier: Programming Language :: Python :: 3.6
License-File: LICENSE
